{
    "id": "installer",
    "path": "",
    "name": "",
    "description": "",
    "sort_order": 0,
    "is_active": 1,
    "is_default": 0,
    "source": "dynamic",
    "home_url": null,
    "domains": [],
    "brand_name": "Webkernel",
    "brand_logo": "/logo.png",
    "brand_logo_dark": "/logo-dark.png",
    "brand_logo_height": "2rem",
    "favicon": null,
    "primary_color": null,
    "sidebar_width": null,
    "collapsed_sidebar_width": null,
    "max_content_width": "xl",
    "sidebar_collapsible": 0,
    "sidebar_fully_collapsible": 0,
    "top_navigation": 0,
    "has_topbar": 1,
    "spa": 0,
    "dark_mode": 1,
    "global_search": 0,
    "broadcasting": 0,
    "database_notifications": 0,
    "unsaved_changes_alerts": 0,
    "database_transactions": 0,
    "auth": 0,
    "registration": 0,
    "password_reset": 0,
    "email_verification": 0,
    "mfa_required": 0,
    "auth_guard": null,
    "auth_password_broker": null,
    "tenant_enabled": 0,
    "tenant_model": null,
    "tenant_ownership_relation": null,
    "tenant_domain": null,
    "tenant_billing": 0,
    "resources": [],
    "pages": [],
    "widgets": [],
    "plugins": [],
    "discover_resources_in": null,
    "discover_resources_for": null,
    "discover_pages_in": null,
    "discover_pages_for": null,
    "discover_widgets_in": null,
    "discover_widgets_for": null,
    "feature_flags": [],
    "extra_middleware": [],
    "extra_auth_middleware": []
}